pod_porter/__init__.py
pod_porter/pod_porter.py
pod_porter/pod_porter_cli.py
pod_porter/version.py
pod_porter/render/__init__.py
pod_porter/render/render.py
pod_porter/render/templates/compose-layout.j2
pod_porter/render/templates/new-map.j2
pod_porter/render/templates/new-porterignore.j2
pod_porter/render/templates/new-service.j2
pod_porter/render/templates/new-values.j2
pod_porter/render/templates/new-volumes.j2
pod_porter/util/__init__.py
pod_porter/util/directories.py
pod_porter/util/file_read_write.py
pod_porter/util/schemas.py
pod_porter-0.2.2.dist-info/licenses/LICENSE
pod_porter-0.2.2.dist-info/METADATA
pod_porter-0.2.2.dist-info/WHEEL
pod_porter-0.2.2.dist-info/entry_points.txt
pod_porter-0.2.2.dist-info/top_level.txt
pod_porter-0.2.2.dist-info/RECORD
