Metadata-Version: 2.4
Name: pod-porter
Version: 0.2.2
Summary: Like Helm but for Container Compose Files
Author-email: "Benjamin P. Trachtenberg" <e_ben_75-python@yahoo.com>
Maintainer-email: "Benjamin P. Trachtenberg" <e_ben_75-python@yahoo.com>
License-Expression: MIT
Project-URL: Documentation, https://pod-porter.readthedocs.io/en/latest/
Project-URL: Source, https://github.com/btr1975/pod-porter
Project-URL: Tracker, https://github.com/btr1975/pod-porter/issues
Keywords: docker,podman,compose,podman-compose,helm,docker-compose,porter,pod-porter
Classifier: Development Status :: 5 - Production/Stable
Classifier: Intended Audience :: Developers
Classifier: Natural Language :: English
Classifier: Operating System :: MacOS :: MacOS X
Classifier: Operating System :: POSIX
Classifier: Operating System :: POSIX :: BSD
Classifier: Operating System :: POSIX :: Linux
Classifier: Operating System :: Microsoft :: Windows
Classifier: Programming Language :: Python :: 3
Classifier: Programming Language :: Python :: 3 :: Only
Classifier: Programming Language :: Python :: 3.9
Classifier: Programming Language :: Python :: 3.10
Classifier: Programming Language :: Python :: 3.11
Classifier: Programming Language :: Python :: 3.12
Classifier: Programming Language :: Python :: 3.13
Requires-Python: <3.14,>=3.9
License-File: LICENSE
Requires-Dist: jinja2~=3.1.4
Requires-Dist: jsonschema[format-nongpl]>=4.23.0
Requires-Dist: pyyaml~=6.0.2
Dynamic: license-file
